unskript/__init__.py
unskript/connectors/__init__.py
unskript/connectors/airflow.py
unskript/connectors/aws.py
unskript/connectors/awsv2.py
unskript/connectors/azure.py
unskript/connectors/chatgpt.py
unskript/connectors/datadog.py
unskript/connectors/elasticsearch.py
unskript/connectors/gcp.py
unskript/connectors/github.py
unskript/connectors/grafana.py
unskript/connectors/hadoop.py
unskript/connectors/infra.py
unskript/connectors/interface.py
unskript/connectors/jenkins.py
unskript/connectors/jira.py
unskript/connectors/k8.py
unskript/connectors/kafka.py
unskript/connectors/mantishub.py
unskript/connectors/mongodb.py
unskript/connectors/ms_sql.py
unskript/connectors/mysql.py
unskript/connectors/netbox.py
unskript/connectors/nomad.py
unskript/connectors/opensearch.py
unskript/connectors/opsgenie.py
unskript/connectors/pingdom.py
unskript/connectors/postgresql.py
unskript/connectors/prometheus.py
unskript/connectors/redis.py
unskript/connectors/rest.py
unskript/connectors/salesforce.py
unskript/connectors/slack.py
unskript/connectors/snowflake.py
unskript/connectors/splunk.py
unskript/connectors/ssh.py
unskript/connectors/stripe.py
unskript/connectors/zabbix.py
unskript/connectors/schema/__init__.py
unskript/connectors/schema/airflow.py
unskript/connectors/schema/aws.py
unskript/connectors/schema/awsv2_schema.py
unskript/connectors/schema/azure.py
unskript/connectors/schema/chatgpt.py
unskript/connectors/schema/datadog.py
unskript/connectors/schema/elasticsearch.py
unskript/connectors/schema/gcp.py
unskript/connectors/schema/github.py
unskript/connectors/schema/grafana.py
unskript/connectors/schema/hadoop.py
unskript/connectors/schema/jenkins.py
unskript/connectors/schema/jira.py
unskript/connectors/schema/k8.py
unskript/connectors/schema/kafka.py
unskript/connectors/schema/mantishub.py
unskript/connectors/schema/mongodb.py
unskript/connectors/schema/ms_sql.py
unskript/connectors/schema/mysql.py
unskript/connectors/schema/netbox.py
unskript_extras-1.0.1456.dist-info/AUTHORS.rst
unskript_extras-1.0.1456.dist-info/LICENSE
unskript_extras-1.0.1456.dist-info/METADATA
unskript_extras-1.0.1456.dist-info/WHEEL
unskript_extras-1.0.1456.dist-info/top_level.txt
unskript_extras-1.0.1456.dist-info/RECORD
