Metadata-Version: 2.1
Name: unskript-extras
Version: 1.0.1456
Summary: Opensource unSkript Python Package repository
Home-page: https://github.com/unskript/unskript.git
Author: unSkript Authors
Author-email: info@unskript.com
License: GNU General Public License v3
Keywords: unskript
Platform: UNKNOWN
Classifier: Development Status :: 2 - Pre-Alpha
Classifier: Intended Audience :: Developers
Classifier: License :: OSI Approved :: GNU General Public License v3 (GPLv3)
Classifier: Natural Language :: English
Classifier: Programming Language :: Python :: 3
Classifier: Programming Language :: Python :: 3.6
Classifier: Programming Language :: Python :: 3.7
Classifier: Programming Language :: Python :: 3.8
Requires-Python: >=3.6
License-File: LICENSE
License-File: AUTHORS.rst
Requires-Dist: opsgenie-sdk (==2.1.4)
Requires-Dist: parallel-ssh (==2.7.0)
Requires-Dist: paramiko (==2.12.0)
Requires-Dist: pynetbox (==7.0.1)
Requires-Dist: python-nomad (==1.5.0)
Requires-Dist: simple-salesforce (==1.12.1)
Requires-Dist: slack-sdk (==3.14.1)
Requires-Dist: stripe (==2.63.0)
